ocrticle/__init__.py
ocrticle/article.py
ocrticle/geometry.py
ocrticle/gui.py
ocrticle/main.py
ocrticle/ocrticle.kv
ocrticle-0.2.0.dist-info/entry_points.txt
ocrticle-0.2.0.dist-info/LICENSE
ocrticle-0.2.0.dist-info/WHEEL
ocrticle-0.2.0.dist-info/METADATA
ocrticle-0.2.0.dist-info/RECORD
